[
  {
    "id": "s1",
    "name": "Serenity Salon & Spa",
    "tagline": "Luxury beauty at its finest",
    "address": "123 Rose Avenue, Downtown",
    "city": "New York",
    "lat": 40.7580,
    "lng": -73.9855,
    "rating": 4.8,
    "reviewCount": 245,
    "coverImage": "https://images.unsplash.com/photo-1600948836101-f3271d530e0f?w=400&h=300&fit=crop",
    "images": [
      "https://images.unsplash.com/photo-1600948836101-f3271d530e0f?w=400&h=300&fit=crop",
      "https://images.unsplash.com/photo-1631299784378-e88afa55d529?w=400&h=300&fit=crop",
      "https://images.unsplash.com/photo-1516975080664-ed2fc6a32937?w=400&h=300&fit=crop",
      "https://images.unsplash.com/photo-1552634534-5f194e4af817?w=400&h=300&fit=crop"
    ],
    "categories": ["Hair", "Makeup", "Spa"],
    "openTime": "09:00",
    "closeTime": "20:00",
    "isOpen": true,
    "distance": 0.8,
    "priceRange": "$$$",
    "serviceIds": ["svc1", "svc2", "svc3", "svc4"],
    "phone": "(555) 123-4567",
    "description": "Premium salon offering hair styling, makeup, and spa services with expert stylists and a luxurious ambiance."
  },
  {
    "id": "s2",
    "name": "Golden Threads Hair Studio",
    "tagline": "Where style meets creativity",
    "address": "456 Fashion Blvd",
    "city": "New York",
    "lat": 40.7489,
    "lng": -73.9680,
    "rating": 4.6,
    "reviewCount": 189,
    "coverImage": "https://images.unsplash.com/photo-1521310503214-7a88fb881ce1?w=400&h=300&fit=crop",
    "images": [
      "https://images.unsplash.com/photo-1521310503214-7a88fb881ce1?w=400&h=300&fit=crop",
      "https://images.unsplash.com/photo-1552374196-c4029bf1b9a0?w=400&h=300&fit=crop",
      "https://images.unsplash.com/photo-1596729251882-ba92c5bfa806?w=400&h=300&fit=crop"
    ],
    "categories": ["Hair", "Bridal"],
    "openTime": "10:00",
    "closeTime": "19:00",
    "isOpen": true,
    "distance": 1.2,
    "priceRange": "$$",
    "serviceIds": ["svc1", "svc5", "svc6"],
    "phone": "(555) 234-5678",
    "description": "Specialist hair salon focused on color, cuts, and bridal styling with award-winning stylists."
  },
  {
    "id": "s3",
    "name": "Nails & Beauty Paradise",
    "tagline": "Perfecting your manicure and pedicure",
    "address": "789 Beauty Lane",
    "city": "New York",
    "lat": 40.7614,
    "lng": -73.9776,
    "rating": 4.5,
    "reviewCount": 156,
    "coverImage": "https://images.unsplash.com/photo-1604654894610-df63bc536371?w=400&h=300&fit=crop",
    "images": [
      "https://images.unsplash.com/photo-1604654894610-df63bc536371?w=400&h=300&fit=crop",
      "https://images.unsplash.com/photo-1611591437281-460bfbe1220a?w=400&h=300&fit=crop",
      "https://images.unsplash.com/photo-1604654842494-87b8d37f4c3e?w=400&h=300&fit=crop"
    ],
    "categories": ["Nails", "Makeup"],
    "openTime": "09:30",
    "closeTime": "19:30",
    "isOpen": false,
    "distance": 2.1,
    "priceRange": "$$",
    "serviceIds": ["svc7", "svc8", "svc9"],
    "phone": "(555) 345-6789",
    "description": "Expert nail care specialists with gel, acrylic, and natural nails services in a welcoming environment."
  },
  {
    "id": "s4",
    "name": "Zen Wellness Spa",
    "tagline": "Holistic relaxation and rejuvenation",
    "address": "321 Wellness Rd",
    "city": "New York",
    "lat": 40.7505,
    "lng": -73.9934,
    "rating": 4.9,
    "reviewCount": 312,
    "coverImage": "https://images.unsplash.com/photo-1540575467063-178f50002c4b?w=400&h=300&fit=crop",
    "images": [
      "https://images.unsplash.com/photo-1540575467063-178f50002c4b?w=400&h=300&fit=crop",
      "https://images.unsplash.com/photo-1600596542815-ffad4c36c44b?w=400&h=300&fit=crop",
      "https://images.unsplash.com/photo-1599643478518-a784e5dc4c8f?w=400&h=300&fit=crop"
    ],
    "categories": ["Spa", "Makeup"],
    "openTime": "08:00",
    "closeTime": "21:00",
    "isOpen": true,
    "distance": 0.5,
    "priceRange": "$$$",
    "serviceIds": ["svc10", "svc11", "svc12"],
    "phone": "(555) 456-7890",
    "description": "Full-service wellness spa offering massages, facials, and body treatments in a serene setting."
  },
  {
    "id": "s5",
    "name": "Glam Makeup Studio",
    "tagline": "Professional makeup for every occasion",
    "address": "555 Glamour St",
    "city": "New York",
    "lat": 40.7549,
    "lng": -73.9840,
    "rating": 4.7,
    "reviewCount": 203,
    "coverImage": "https://images.unsplash.com/photo-1596729251882-ba92c5bfa806?w=400&h=300&fit=crop",
    "images": [
      "https://images.unsplash.com/photo-1596729251882-ba92c5bfa806?w=400&h=300&fit=crop",
      "https://images.unsplash.com/photo-1552746236-e540132ce33d?w=400&h=300&fit=crop",
      "https://images.unsplash.com/photo-1554411593-4628191b2890?w=400&h=300&fit=crop"
    ],
    "categories": ["Makeup", "Bridal"],
    "openTime": "10:00",
    "closeTime": "20:00",
    "isOpen": true,
    "distance": 1.8,
    "priceRange": "$$",
    "serviceIds": ["svc13", "svc14", "svc15"],
    "phone": "(555) 567-8901",
    "description": "Expert makeup artists specializing in bridal, special events, and daily looks using premium products."
  },
  {
    "id": "s6",
    "name": "Hair Dynasty Studio",
    "tagline": "Transforming locks, changing lives",
    "address": "888 Crown Plaza",
    "city": "New York",
    "lat": 40.7282,
    "lng": -73.7949,
    "rating": 4.4,
    "reviewCount": 134,
    "coverImage": "https://images.unsplash.com/photo-1507003211169-0a1dd7228f2d?w=400&h=300&fit=crop",
    "images": [
      "https://images.unsplash.com/photo-1507003211169-0a1dd7228f2d?w=400&h=300&fit=crop",
      "https://images.unsplash.com/photo-1507634712202-c61b23f0b5fb?w=400&h=300&fit=crop",
      "https://images.unsplash.com/photo-1508963795882-a38efafc620d?w=400&h=300&fit=crop"
    ],
    "categories": ["Hair"],
    "openTime": "11:00",
    "closeTime": "18:00",
    "isOpen": true,
    "distance": 3.2,
    "priceRange": "$",
    "serviceIds": ["svc1", "svc16", "svc17"],
    "phone": "(555) 678-9012",
    "description": "Affordable hair salon with expert stylists offering cuts, colors, and treatments."
  },
  {
    "id": "s7",
    "name": "Radiant Beauty Boutique",
    "tagline": "Your complete beauty destination",
    "address": "999 Elegance Way",
    "city": "New York",
    "lat": 40.7308,
    "lng": -73.9352,
    "rating": 4.8,
    "reviewCount": 267,
    "coverImage": "https://images.unsplash.com/photo-1553903981-e32dcc44f14f?w=400&h=300&fit=crop",
    "images": [
      "https://images.unsplash.com/photo-1553903981-e32dcc44f14f?w=400&h=300&fit=crop",
      "https://images.unsplash.com/photo-1552641554-5fefe8c9ef14?w=400&h=300&fit=crop",
      "https://images.unsplash.com/photo-1599643478518-a784e5dc4c8f?w=400&h=300&fit=crop"
    ],
    "categories": ["Hair", "Nails", "Makeup", "Spa"],
    "openTime": "09:00",
    "closeTime": "21:00",
    "isOpen": true,
    "distance": 2.3,
    "priceRange": "$$$",
    "serviceIds": ["svc1", "svc7", "svc13", "svc10"],
    "phone": "(555) 789-0123",
    "description": "Full-service beauty boutique offering hair, nails, makeup, and spa treatments under one roof."
  },
  {
    "id": "s8",
    "name": "Stylish Cuts Barbershop",
    "tagline": "Traditional cuts with modern flair",
    "address": "111 Barber Ave",
    "city": "New York",
    "lat": 40.7580,
    "lng": -73.9855,
    "rating": 4.3,
    "reviewCount": 98,
    "coverImage": "https://images.unsplash.com/photo-1585747860715-cd4628902d4a?w=400&h=300&fit=crop",
    "images": [
      "https://images.unsplash.com/photo-1585747860715-cd4628902d4a?w=400&h=300&fit=crop",
      "https://images.unsplash.com/photo-1503235930437-8c6293ba41f3?w=400&h=300&fit=crop"
    ],
    "categories": ["Hair"],
    "openTime": "08:00",
    "closeTime": "18:00",
    "isOpen": false,
    "distance": 1.5,
    "priceRange": "$",
    "serviceIds": ["svc16", "svc17"],
    "phone": "(555) 890-1234",
    "description": "Professional barbershop with experienced barbers offering precision cuts and grooming."
  }
]

